chaoscloud/__init__.py
chaoscloud/__main__.py
chaoscloud/cli.py
chaoscloud/controls.py
chaoscloud/exceptions.py
chaoscloud/extension.py
chaoscloud/settings.py
chaoscloud/types.py
chaoscloud/workspace.py
chaoscloud/api/__init__.py
chaoscloud/api/execution.py
chaoscloud/api/experiment.py
chaoscloud/api/organization.py
chaoscloud/api/safeguard.py
chaoscloud/api/ssl.py
chaoscloud/api/team.py
chaoscloud/api/urls.py
chaoscloud/api/verification.py
chaoscloud/probes/__init__.py
chaoscloud/probes/http.py
chaoscloud/tolerances/__init__.py
chaoscloud/tolerances/http.py
chaoscloud/tolerances/prometheus.py
chaoscloud/verify/__init__.py
chaoscloud/verify/exceptions.py
chaoscloud/verify/verification.py
chaosiq_cloud-0.16.0.dist-info/LICENSE
chaosiq_cloud-0.16.0.dist-info/METADATA
chaosiq_cloud-0.16.0.dist-info/WHEEL
chaosiq_cloud-0.16.0.dist-info/entry_points.txt
chaosiq_cloud-0.16.0.dist-info/top_level.txt
chaosiq_cloud-0.16.0.dist-info/RECORD
