Metadata-Version: 2.1
Name: chaosiq-cloud
Version: 0.16.0
Summary: ChaosIQ plugin for the Chaos Toolkit CLI
Home-page: https://chaosiq.io
Author: ChaosIQ
Author-email: contact@chaosiq.io
License: Apache License Version 2.0
Platform: UNKNOWN
Classifier: Intended Audience :: Developers
Classifier: License :: Freely Distributable
Classifier: Operating System :: OS Independent
Classifier: License :: OSI Approved :: Apache Software License
Classifier: Programming Language :: Python
Classifier: Programming Language :: Python :: 3
Classifier: Programming Language :: Python :: 3.6
Classifier: Programming Language :: Python :: 3.7
Classifier: Programming Language :: Python :: 3.8
Classifier: Programming Language :: Python :: Implementation
Classifier: Programming Language :: Python :: Implementation :: CPython
Requires-Python: >=3.6.*
Requires-Dist: chaostoolkit-lib (~=1.22)
Requires-Dist: chaostoolkit (~=1.10)
Requires-Dist: click (~=7.0)
Requires-Dist: logzero (~=1.5)
Requires-Dist: requests (~=2.21)
Requires-Dist: simplejson (~=3.16)
Requires-Dist: pyyaml (~=5.0)
Requires-Dist: tzlocal (~=1.5)
Requires-Dist: pytz
Requires-Dist: cloudevents (==0.3) ; python_version < "3.6"
Requires-Dist: cloudevents (~=1.2) ; python_version >= "3.6"
